{"level":"info","ts":"2022-11-10T00:13:34.716+0700","caller":"rest_api/hello.go:35","msg":"demo","traceId":"d64b432c8f9e32dd4aa35c556c5da806"}
{"level":"info","ts":"2022-11-10T00:18:21.460+0700","caller":"rest_api/hello.go:35","msg":"demo","traceId":"b635a2bea1593234b4cd372033e51350"}
{"level":"info","ts":"2022-11-10T00:18:22.719+0700","caller":"rest_api/hello.go:35","msg":"demo","traceId":"7e89bb205ad00a1efaab8a97945b3ba4"}
{"level":"info","ts":"2022-11-10T00:18:22.958+0700","caller":"rest_api/hello.go:35","msg":"demo","traceId":"23832e1191ab4724487caf78b13a2fa8"}
{"level":"info","ts":"2022-11-10T00:18:23.162+0700","caller":"rest_api/hello.go:35","msg":"demo","traceId":"38170246aad504edb6f2c505e348eb8b"}
{"level":"info","ts":"2022-11-10T00:18:23.359+0700","caller":"rest_api/hello.go:35","msg":"demo","traceId":"8338a2665d70256bd1f32eac01b983c9"}
{"level":"info","ts":"2022-11-10T00:23:42.279+0700","caller":"rest_api/hello.go:35","msg":"demo","traceId":"478d823f9638774cc4b1d1e6f8ca36cd"}
{"level":"info","ts":"2022-11-10T00:23:42.855+0700","caller":"rest_api/hello.go:35","msg":"demo","traceId":"ecc5000c8933005732682b8b1385bf4d"}
{"level":"info","ts":"2022-11-10T00:23:43.062+0700","caller":"rest_api/hello.go:35","msg":"demo","traceId":"b1556f53662796ee740b20d054649f05"}
{"level":"info","ts":"2022-11-10T00:23:43.232+0700","caller":"rest_api/hello.go:35","msg":"demo","traceId":"44c51ee3833fb8aaa820effe5cc7a519"}
{"level":"info","ts":"2022-11-10T00:23:43.407+0700","caller":"rest_api/hello.go:35","msg":"demo","traceId":"026360dedd42b61225c6254645dce4cc"}
{"level":"info","ts":"2022-11-10T00:23:43.570+0700","caller":"rest_api/hello.go:35","msg":"demo","traceId":"8463a7db69b563f33d83f36d8e928c6d"}
{"level":"info","ts":"2022-11-10T00:23:43.755+0700","caller":"rest_api/hello.go:35","msg":"demo","traceId":"cfcb06a3fb8ea85842f18966ecfb0327"}
{"level":"info","ts":"2022-11-10T00:28:45.455+0700","caller":"rest_api/hello.go:35","msg":"demo","traceId":"d75cc2e7521634dd5d2defb97b76fbff"}
{"level":"info","ts":"2022-11-10T00:28:45.656+0700","caller":"rest_api/hello.go:35","msg":"demo","traceId":"213f880b7a11c36133548e03c669d51a"}
{"level":"info","ts":"2022-11-10T00:28:45.833+0700","caller":"rest_api/hello.go:35","msg":"demo","traceId":"21ec5df428771885f762bf880342b3a5"}
{"level":"info","ts":"2022-11-10T00:28:46.028+0700","caller":"rest_api/hello.go:35","msg":"demo","traceId":"75bbf73784f39d76eef809711cf05d8c"}
{"level":"info","ts":"2022-11-10T00:28:46.207+0700","caller":"rest_api/hello.go:35","msg":"demo","traceId":"ca1f6e59c30845878dacdea25856a986"}
{"level":"info","ts":"2022-11-10T00:28:46.405+0700","caller":"rest_api/hello.go:35","msg":"demo","traceId":"ef5b290f5f29c20b0f98ffafc3b841d6"}
{"level":"info","ts":"2022-11-10T00:28:46.580+0700","caller":"rest_api/hello.go:35","msg":"demo","traceId":"5e4b58bd0638ce34699687fca6a647ee"}
{"level":"info","ts":"2022-11-10T00:36:21.225+0700","caller":"rest_api/hello.go:35","msg":"demo","traceId":"d9cb54b9ebd9b60b3e2d7c9e1e19e2f4"}
{"level":"info","ts":"2022-11-10T00:36:21.759+0700","caller":"rest_api/hello.go:35","msg":"demo","traceId":"965a814a5519158a3cb47ffc474094c9"}
{"level":"info","ts":"2022-11-10T00:36:21.933+0700","caller":"rest_api/hello.go:35","msg":"demo","traceId":"837e331d928b7d0240144482216a6cc1"}
{"level":"info","ts":"2022-11-10T00:36:22.111+0700","caller":"rest_api/hello.go:35","msg":"demo","traceId":"c41bf29dee35929e65d8251e2d1f7d1a"}
{"level":"info","ts":"2022-11-10T00:36:22.281+0700","caller":"rest_api/hello.go:35","msg":"demo","traceId":"1be2c1a94bcbc13646bb9e745f038899"}
{"level":"info","ts":"2022-11-10T00:36:22.476+0700","caller":"rest_api/hello.go:35","msg":"demo","traceId":"e5c592e35d05a08c8d8d6ec8c1664b5d"}
{"level":"info","ts":"2022-11-10T00:36:22.658+0700","caller":"rest_api/hello.go:35","msg":"demo","traceId":"dcb80f4ded0b2bd622dd34bfb7597248"}
{"level":"info","ts":"2022-11-10T00:36:22.832+0700","caller":"rest_api/hello.go:35","msg":"demo","traceId":"241817317d45d16fb8a79b8169134d06"}
{"level":"info","ts":"2022-11-10T00:36:23.006+0700","caller":"rest_api/hello.go:35","msg":"demo","traceId":"42052315d9b8ce9c9ec2cae7e865add7"}
{"level":"info","ts":"2022-11-10T00:36:23.169+0700","caller":"rest_api/hello.go:35","msg":"demo","traceId":"a4de0e58dd61f4b4c5dcdde63fde11f8"}
{"level":"info","ts":"2022-11-10T00:39:40.030+0700","caller":"rest_api/hello.go:35","msg":"demo","traceId":"1eebb84545d36f90809c22fa3e18a4d2"}
{"level":"info","ts":"2022-11-10T00:39:40.260+0700","caller":"rest_api/hello.go:35","msg":"demo","traceId":"b5598af66399fe28c2d57829b15d7d9c"}
{"level":"info","ts":"2022-11-10T00:39:40.461+0700","caller":"rest_api/hello.go:35","msg":"demo","traceId":"66d149938df674e39c36a2e1a29ad658"}
{"level":"info","ts":"2022-11-10T00:39:40.629+0700","caller":"rest_api/hello.go:35","msg":"demo","traceId":"6fa5b481e5e2362b58b32901968a7c3d"}
{"level":"info","ts":"2022-11-10T00:39:40.817+0700","caller":"rest_api/hello.go:35","msg":"demo","traceId":"1fc379211659de546b09ab5ff774d1c8"}
{"level":"info","ts":"2022-11-10T00:39:41.015+0700","caller":"rest_api/hello.go:35","msg":"demo","traceId":"3e1354257883433cf1564be7732cb0df"}
{"level":"info","ts":"2022-11-10T00:39:41.185+0700","caller":"rest_api/hello.go:35","msg":"demo","traceId":"ee133c99cda422b778fd0bcdc4474d98"}
{"level":"info","ts":"2022-11-10T00:40:03.264+0700","caller":"rest_api/hello.go:35","msg":"demo","traceId":"5e1e980b599e9ecdc62a33f9f2df3715"}
{"level":"info","ts":"2022-11-10T00:40:03.515+0700","caller":"rest_api/hello.go:35","msg":"demo","traceId":"34a99159c8bdef67a148c7b85a51611d"}
{"level":"info","ts":"2022-11-10T00:40:03.687+0700","caller":"rest_api/hello.go:35","msg":"demo","traceId":"4581d384c2a72815db237458bcfebb62"}
{"level":"info","ts":"2022-11-10T00:40:03.886+0700","caller":"rest_api/hello.go:35","msg":"demo","traceId":"74e190f845785cfd4198a4cd93af4073"}
{"level":"info","ts":"2022-11-10T00:40:44.479+0700","caller":"rest_api/hello.go:35","msg":"demo","traceId":"b0e2aa26ec25a83f4a5c6946715856ea"}
{"level":"info","ts":"2022-11-10T07:50:51.121+0700","caller":"rest_api/hello.go:35","msg":"demo","traceId":"007611e9aba4cf5a8df2d4e8e299eef0"}
{"level":"info","ts":"2022-11-10T07:50:51.367+0700","caller":"rest_api/hello.go:35","msg":"demo","traceId":"3a01fbf19f0f47eedaf68e21f634a923"}
{"level":"info","ts":"2022-11-10T07:50:51.574+0700","caller":"rest_api/hello.go:35","msg":"demo","traceId":"2970f7c8480e31fd78301875c4f681fe"}
{"level":"info","ts":"2022-11-10T07:50:51.802+0700","caller":"rest_api/hello.go:35","msg":"demo","traceId":"89ab53192fd568519a6cd5a42002c017"}
{"level":"info","ts":"2022-11-10T07:50:51.995+0700","caller":"rest_api/hello.go:35","msg":"demo","traceId":"fe54cbef49402e396686c06b2742696a"}
{"level":"info","ts":"2022-11-10T07:57:45.350+0700","caller":"rest_api/hello.go:34","msg":"demo","traceId":"2ac233e2b26bd89f1fe7a3a4351b817a"}
{"level":"info","ts":"2022-11-10T07:57:45.839+0700","caller":"rest_api/hello.go:34","msg":"demo","traceId":"03c26f3e3d4baf20e8d45894eef444f1"}
{"level":"info","ts":"2022-11-10T07:57:46.046+0700","caller":"rest_api/hello.go:34","msg":"demo","traceId":"ee1595d6969c6880d0cbd28bb1ca940c"}
{"level":"info","ts":"2022-11-10T07:57:46.245+0700","caller":"rest_api/hello.go:34","msg":"demo","traceId":"362381bc0858624dc82223ed00d7de03"}
